MANIFEST.in
setup.py
docs/HISTORY.txt
src/dolmen/__init__.py
src/dolmen.field.egg-info/PKG-INFO
src/dolmen.field.egg-info/SOURCES.txt
src/dolmen.field.egg-info/dependency_links.txt
src/dolmen.field.egg-info/namespace_packages.txt
src/dolmen.field.egg-info/not-zip-safe
src/dolmen.field.egg-info/requires.txt
src/dolmen.field.egg-info/top_level.txt
src/dolmen/field/README.txt
src/dolmen/field/__init__.py
src/dolmen/field/fields.py
src/dolmen/field/interfaces.py
src/dolmen/field/tests.py