Metadata-Version: 1.0
Name: dolmen.field
Version: 0.3
Summary: Generic Formlib fields
Home-page: http://gitweb.dolmen-project.org
Author: Souheil Chelfouh
Author-email: trollfot@gmail.com
License: GPL
Download-URL: http://pypi.python.org/pypi/dolmen.field
Keywords: Grok Zope3 Dolmen
Platform: Any
Classifier: Development Status :: 4 - Beta
Classifier: Environment :: Web Environment
Classifier: Intended Audience :: Other Audience
Classifier: License :: OSI Approved :: GNU General Public License (GPL)
Classifier: Operating System :: OS Independent
Classifier: Programming Language :: Python
